dash/htmlayout/__init__.py
dash/htmlayout/builder.py
dash/htmlayout/converters.py
dash_htmlayout-1.0.5.dist-info/LICENSE
dash_htmlayout-1.0.5.dist-info/METADATA
dash_htmlayout-1.0.5.dist-info/WHEEL
dash_htmlayout-1.0.5.dist-info/top_level.txt
dash_htmlayout-1.0.5.dist-info/RECORD
