Metadata-Version: 2.1
Name: dash-htmlayout
Version: 1.0.5
Summary: Build HTML layouts in Dash with HTML
Author-email: Steve Kossouho <noreply@example.com>
Project-URL: Homepage, https://github.com/artscoop/dash-htmlayout
Project-URL: Documentation, https://artscoop.github.io/dash-htmlayout/htmlayout.html
Project-URL: Bug Tracker, https://github.com/artscoop/dash-htmlayout/issues
Classifier: Programming Language :: Python :: 3
Classifier: License :: OSI Approved :: MIT License
Classifier: Operating System :: OS Independent
Requires-Python: >=3.9
License-File: LICENSE
Requires-Dist: lxml
Requires-Dist: dash >=2.0.0
